deepler/__init__.py
deepler/cli.py
deepler/constants.py
deepler/core/__init__.py
deepler/core/configuration.py
deepler/core/histogram.py
deepler/core/translator.py
deepler/core/word_splitter.py
deepler-0.1.2.dist-info/METADATA
deepler-0.1.2.dist-info/WHEEL
deepler-0.1.2.dist-info/entry_points.txt
deepler-0.1.2.dist-info/RECORD
