Metadata-Version: 2.1
Name: deepler
Version: 0.1.2
Summary: deepler is a learning support tool that records the number of words that appear through DeepL. You can learn frequently used words efficiently.
Home-page: https://github.com/rhoboro/deepler
License: MIT
Author: rhoboro
Author-email: rhoboro@gmail.com
Requires-Python: >=3.9,<4.0
Classifier: Development Status :: 3 - Alpha
Classifier: Environment :: Console
Classifier: Intended Audience :: Education
Classifier: License :: OSI Approved :: MIT License
Classifier: Operating System :: OS Independent
Classifier: Programming Language :: Python :: 3
Classifier: Programming Language :: Python :: 3.9
Classifier: Programming Language :: Python :: 3.10
Classifier: Programming Language :: Python :: 3.11
Classifier: Topic :: Education
Requires-Dist: deepl (>=1.15.0,<2.0.0)
Project-URL: Repository, https://github.com/rhoboro/deepler
